README.md
daab.py
setup.py
daab.egg-info/PKG-INFO
daab.egg-info/SOURCES.txt
daab.egg-info/dependency_links.txt
daab.egg-info/requires.txt
daab.egg-info/top_level.txt