Metadata-Version: 2.1
Name: daab
Version: 1.0.0
Summary: DNS as a database.
Home-page: https://github.com/beanpuppy/dns-as-a-database
Author: Justin Duch
Author-email: justin@justinduch.com
License: MIT
Keywords: database dns
Platform: UNKNOWN
Classifier: Development Status :: 5 - Production/Stable
Classifier: Intended Audience :: Developers
Classifier: Topic :: Software Development :: Libraries :: Python Modules
Classifier: License :: OSI Approved :: MIT License
Classifier: Programming Language :: Python :: 3
Classifier: Programming Language :: Python :: 3.4
Classifier: Programming Language :: Python :: 3.5
Classifier: Programming Language :: Python :: 3.6
Classifier: Programming Language :: Python :: 3.7
